[
    {
      "inputs": [],
      "stateMutability": "nonpayable",
      "type": "constructor"
    },
    {
      "inputs": [],
      "name": "AccessControlBadConfirmation",
      "type": "error"
    },
    {
      "inputs": [
        {
          "internalType": "address",
          "name": "account",
          "type": "address"
        },
        {
          "internalType": "bytes32",
          "name": "neededRole",
          "type": "bytes32"
        }
      ],
      "name": "AccessControlUnauthorizedAccount",
      "type": "error"
    },
    {
      "inputs": [],
      "name": "ContractNotSet",
      "type": "error"
    },
    {
      "inputs": [],
      "name": "InsufficientFunds",
      "type": "error"
    },
    {
      "inputs": [],
      "name": "InvalidInitialization",
      "type": "error"
    },
    {
      "inputs": [],
      "name": "InvalidParameters",
      "type": "error"
    },
    {
      "inputs": [],
      "name": "InvalidProjectId",
      "type": "error"
    },
    {
      "inputs": [],
      "name": "InvalidProjectState",
      "type": "error"
    },
    {
      "inputs": [],
      "name": "NotInitializing",
      "type": "error"
    },
    {
      "inputs": [],
      "name": "ProjectAlreadyExists",
      "type": "error"
    },
    {
      "inputs": [],
      "name": "ReentrancyGuardReentrantCall",
      "type": "error"
    },
    {
      "inputs": [],
      "name": "UnauthorizedAccess",
      "type": "error"
    },
    {
      "anonymous": false,
      "inputs": [
        {
          "indexed": true,
          "internalType": "enum ITerraStakeProjects.ProjectCategory",
          "name": "category",
          "type": "uint8"
        },
        {
          "indexed": false,
          "internalType": "uint256",
          "name": "multiplier",
          "type": "uint256"
        }
      ],
      "name": "CategoryMultiplierUpdated",
      "type": "event"
    },
    {
      "anonymous": false,
      "inputs": [
        {
          "indexed": false,
          "internalType": "address",
          "name": "stakingContract",
          "type": "address"
        },
        {
          "indexed": false,
          "internalType": "address",
          "name": "rewardsContract",
          "type": "address"
        }
      ],
      "name": "ContractsSet",
      "type": "event"
    },
    {
      "anonymous": false,
      "inputs": [
        {
          "indexed": true,
          "internalType": "uint256",
          "name": "projectId",
          "type": "uint256"
        },
        {
          "indexed": false,
          "internalType": "bytes32[]",
          "name": "documentHashes",
          "type": "bytes32[]"
        }
      ],
      "name": "DocumentationUpdated",
      "type": "event"
    },
    {
      "anonymous": false,
      "inputs": [
        {
          "indexed": true,
          "internalType": "enum ITerraStakeProjects.ProjectCategory",
          "name": "category",
          "type": "uint8"
        },
        {
          "indexed": false,
          "internalType": "uint256",
          "name": "minimumImpact",
          "type": "uint256"
        }
      ],
      "name": "ImpactRequirementUpdated",
      "type": "event"
    },
    {
      "anonymous": false,
      "inputs": [
        {
          "indexed": false,
          "internalType": "uint64",
          "name": "version",
          "type": "uint64"
        }
      ],
      "name": "Initialized",
      "type": "event"
    },
    {
      "anonymous": false,
      "inputs": [
        {
          "indexed": true,
          "internalType": "uint256",
          "name": "projectId",
          "type": "uint256"
        },
        {
          "indexed": false,
          "internalType": "string",
          "name": "metricType",
          "type": "string"
        },
        {
          "indexed": false,
          "internalType": "string",
          "name": "metricValue",
          "type": "string"
        }
      ],
      "name": "MetricsReported",
      "type": "event"
    },
    {
      "anonymous": false,
      "inputs": [
        {
          "indexed": true,
          "internalType": "uint256",
          "name": "projectId",
          "type": "uint256"
        },
        {
          "indexed": false,
          "internalType": "string",
          "name": "name",
          "type": "string"
        },
        {
          "indexed": false,
          "internalType": "enum ITerraStakeProjects.ProjectCategory",
          "name": "category",
          "type": "uint8"
        }
      ],
      "name": "ProjectAdded",
      "type": "event"
    },
    {
      "anonymous": false,
      "inputs": [
        {
          "indexed": true,
          "internalType": "uint256",
          "name": "projectId",
          "type": "uint256"
        },
        {
          "indexed": true,
          "internalType": "enum ITerraStakeProjects.ProjectState",
          "name": "oldState",
          "type": "uint8"
        },
        {
          "indexed": true,
          "internalType": "enum ITerraStakeProjects.ProjectState",
          "name": "newState",
          "type": "uint8"
        }
      ],
      "name": "ProjectStateChanged",
      "type": "event"
    },
    {
      "anonymous": false,
      "inputs": [
        {
          "indexed": true,
          "internalType": "uint256",
          "name": "projectId",
          "type": "uint256"
        },
        {
          "indexed": false,
          "internalType": "string",
          "name": "name",
          "type": "string"
        }
      ],
      "name": "ProjectUpdated",
      "type": "event"
    },
    {
      "anonymous": false,
      "inputs": [
        {
          "indexed": true,
          "internalType": "bytes32",
          "name": "role",
          "type": "bytes32"
        },
        {
          "indexed": true,
          "internalType": "bytes32",
          "name": "previousAdminRole",
          "type": "bytes32"
        },
        {
          "indexed": true,
          "internalType": "bytes32",
          "name": "newAdminRole",
          "type": "bytes32"
        }
      ],
      "name": "RoleAdminChanged",
      "type": "event"
    },
    {
      "anonymous": false,
      "inputs": [
        {
          "indexed": true,
          "internalType": "bytes32",
          "name": "role",
          "type": "bytes32"
        },
        {
          "indexed": true,
          "internalType": "address",
          "name": "account",
          "type": "address"
        },
        {
          "indexed": true,
          "internalType": "address",
          "name": "sender",
          "type": "address"
        }
      ],
      "name": "RoleGranted",
      "type": "event"
    },
    {
      "anonymous": false,
      "inputs": [
        {
          "indexed": true,
          "internalType": "bytes32",
          "name": "role",
          "type": "bytes32"
        },
        {
          "indexed": true,
          "internalType": "address",
          "name": "account",
          "type": "address"
        },
        {
          "indexed": true,
          "internalType": "address",
          "name": "sender",
          "type": "address"
        }
      ],
      "name": "RoleRevoked",
      "type": "event"
    },
    {
      "anonymous": false,
      "inputs": [
        {
          "indexed": true,
          "internalType": "uint256",
          "name": "projectId",
          "type": "uint256"
        },
        {
          "indexed": true,
          "internalType": "address",
          "name": "vvb",
          "type": "address"
        },
        {
          "indexed": false,
          "internalType": "bytes32",
          "name": "reportHash",
          "type": "bytes32"
        }
      ],
      "name": "ValidationSubmitted",
      "type": "event"
    },
    {
      "anonymous": false,
      "inputs": [
        {
          "indexed": true,
          "internalType": "uint256",
          "name": "projectId",
          "type": "uint256"
        },
        {
          "indexed": true,
          "internalType": "address",
          "name": "vvb",
          "type": "address"
        },
        {
          "indexed": false,
          "internalType": "bytes32",
          "name": "reportHash",
          "type": "bytes32"
        }
      ],
      "name": "VerificationSubmitted",
      "type": "event"
    },
    {
      "inputs": [],
      "name": "DEFAULT_ADMIN_ROLE",
      "outputs": [
        {
          "internalType": "bytes32",
          "name": "",
          "type": "bytes32"
        }
      ],
      "stateMutability": "view",
      "type": "function"
    },
    {
      "inputs": [],
      "name": "FEED_UPDATE_ROLE",
      "outputs": [
        {
          "internalType": "bytes32",
          "name": "",
          "type": "bytes32"
        }
      ],
      "stateMutability": "view",
      "type": "function"
    },
    {
      "inputs": [],
      "name": "PROJECT_MANAGER_ROLE",
      "outputs": [
        {
          "internalType": "bytes32",
          "name": "",
          "type": "bytes32"
        }
      ],
      "stateMutability": "view",
      "type": "function"
    },
    {
      "inputs": [],
      "name": "REWARD_MANAGER_ROLE",
      "outputs": [
        {
          "internalType": "bytes32",
          "name": "",
          "type": "bytes32"
        }
      ],
      "stateMutability": "view",
      "type": "function"
    },
    {
      "inputs": [],
      "name": "VALIDATOR_ROLE",
      "outputs": [
        {
          "internalType": "bytes32",
          "name": "",
          "type": "bytes32"
        }
      ],
      "stateMutability": "view",
      "type": "function"
    },
    {
      "inputs": [
        {
          "internalType": "string",
          "name": "name",
          "type": "string"
        },
        {
          "internalType": "string",
          "name": "description",
          "type": "string"
        },
        {
          "internalType": "string",
          "name": "location",
          "type": "string"
        },
        {
          "internalType": "string",
          "name": "impactMetrics",
          "type": "string"
        },
        {
          "internalType": "bytes32",
          "name": "ipfsHash",
          "type": "bytes32"
        },
        {
          "internalType": "enum ITerraStakeProjects.ProjectCategory",
          "name": "category",
          "type": "uint8"
        },
        {
          "internalType": "uint32",
          "name": "stakingMultiplier",
          "type": "uint32"
        },
        {
          "internalType": "uint48",
          "name": "startBlock",
          "type": "uint48"
        },
        {
          "internalType": "uint48",
          "name": "endBlock",
          "type": "uint48"
        }
      ],
      "name": "addProject",
      "outputs": [],
      "stateMutability": "payable",
      "type": "function"
    },
    {
      "inputs": [
        {
          "internalType": "enum ITerraStakeProjects.ProjectCategory",
          "name": "",
          "type": "uint8"
        }
      ],
      "name": "categoryRequirements",
      "outputs": [
        {
          "internalType": "uint256",
          "name": "minimumImpact",
          "type": "uint256"
        },
        {
          "internalType": "uint256",
          "name": "verificationFrequency",
          "type": "uint256"
        },
        {
          "internalType": "uint256",
          "name": "qualityThreshold",
          "type": "uint256"
        },
        {
          "internalType": "uint256",
          "name": "minimumScale",
          "type": "uint256"
        }
      ],
      "stateMutability": "view",
      "type": "function"
    },
    {
      "inputs": [
        {
          "internalType": "uint256",
          "name": "",
          "type": "uint256"
        }
      ],
      "name": "generalProjectMetadata",
      "outputs": [
        {
          "internalType": "uint48",
          "name": "startDate",
          "type": "uint48"
        },
        {
          "internalType": "uint48",
          "name": "endDate",
          "type": "uint48"
        },
        {
          "internalType": "uint256",
          "name": "budgetAllocation",
          "type": "uint256"
        },
        {
          "internalType": "string",
          "name": "riskAssessment",
          "type": "string"
        },
        {
          "internalType": "string",
          "name": "complianceDocumentation",
          "type": "string"
        }
      ],
      "stateMutability": "view",
      "type": "function"
    },
    {
      "inputs": [
        {
          "internalType": "enum ITerraStakeProjects.ProjectCategory",
          "name": "category",
          "type": "uint8"
        }
      ],
      "name": "getCategoryRequirements",
      "outputs": [
        {
          "components": [
            {
              "internalType": "uint256",
              "name": "minimumImpact",
              "type": "uint256"
            },
            {
              "internalType": "uint256",
              "name": "verificationFrequency",
              "type": "uint256"
            },
            {
              "internalType": "string[]",
              "name": "requiredDocuments",
              "type": "string[]"
            },
            {
              "internalType": "uint256",
              "name": "qualityThreshold",
              "type": "uint256"
            },
            {
              "internalType": "uint256",
              "name": "minimumScale",
              "type": "uint256"
            }
          ],
          "internalType": "struct ITerraStakeProjects.ImpactRequirement",
          "name": "",
          "type": "tuple"
        }
      ],
      "stateMutability": "view",
      "type": "function"
    },
    {
      "inputs": [],
      "name": "getProjectCount",
      "outputs": [
        {
          "internalType": "uint256",
          "name": "",
          "type": "uint256"
        }
      ],
      "stateMutability": "view",
      "type": "function"
    },
    {
      "inputs": [
        {
          "internalType": "uint256",
          "name": "projectId",
          "type": "uint256"
        }
      ],
      "name": "getProjectDetails",
      "outputs": [
        {
          "components": [
            {
              "internalType": "string",
              "name": "name",
              "type": "string"
            },
            {
              "internalType": "string",
              "name": "description",
              "type": "string"
            },
            {
              "internalType": "string",
              "name": "location",
              "type": "string"
            },
            {
              "internalType": "string",
              "name": "impactMetrics",
              "type": "string"
            },
            {
              "internalType": "bytes32",
              "name": "ipfsHash",
              "type": "bytes32"
            },
            {
              "internalType": "bool",
              "name": "exists",
              "type": "bool"
            }
          ],
          "internalType": "struct ITerraStakeProjects.ProjectData",
          "name": "",
          "type": "tuple"
        }
      ],
      "stateMutability": "view",
      "type": "function"
    },
    {
      "inputs": [
        {
          "internalType": "uint256",
          "name": "projectId",
          "type": "uint256"
        }
      ],
      "name": "getProjectState",
      "outputs": [
        {
          "components": [
            {
              "internalType": "enum ITerraStakeProjects.ProjectCategory",
              "name": "category",
              "type": "uint8"
            },
            {
              "internalType": "enum ITerraStakeProjects.ProjectState",
              "name": "state",
              "type": "uint8"
            },
            {
              "internalType": "uint32",
              "name": "stakingMultiplier",
              "type": "uint32"
            },
            {
              "internalType": "uint128",
              "name": "totalStaked",
              "type": "uint128"
            },
            {
              "internalType": "uint128",
              "name": "rewardPool",
              "type": "uint128"
            },
            {
              "internalType": "bool",
              "name": "isActive",
              "type": "bool"
            },
            {
              "internalType": "uint48",
              "name": "startBlock",
              "type": "uint48"
            },
            {
              "internalType": "uint48",
              "name": "endBlock",
              "type": "uint48"
            },
            {
              "internalType": "address",
              "name": "owner",
              "type": "address"
            },
            {
              "internalType": "int256",
              "name": "lastReportedValue",
              "type": "int256"
            },
            {
              "internalType": "uint256",
              "name": "lastRewardUpdate",
              "type": "uint256"
            },
            {
              "internalType": "uint256",
              "name": "accumulatedRewards",
              "type": "uint256"
            }
          ],
          "internalType": "struct ITerraStakeProjects.ProjectStateData",
          "name": "",
          "type": "tuple"
        }
      ],
      "stateMutability": "view",
      "type": "function"
    },
    {
      "inputs": [
        {
          "internalType": "bytes32",
          "name": "role",
          "type": "bytes32"
        }
      ],
      "name": "getRoleAdmin",
      "outputs": [
        {
          "internalType": "bytes32",
          "name": "",
          "type": "bytes32"
        }
      ],
      "stateMutability": "view",
      "type": "function"
    },
    {
      "inputs": [
        {
          "internalType": "uint256",
          "name": "projectId",
          "type": "uint256"
        }
      ],
      "name": "getValidationReport",
      "outputs": [
        {
          "components": [
            {
              "internalType": "address",
              "name": "vvb",
              "type": "address"
            },
            {
              "internalType": "uint256",
              "name": "validationDate",
              "type": "uint256"
            },
            {
              "internalType": "bytes32",
              "name": "validationReportHash",
              "type": "bytes32"
            }
          ],
          "internalType": "struct TerraStakeProjects.ValidationData",
          "name": "",
          "type": "tuple"
        }
      ],
      "stateMutability": "view",
      "type": "function"
    },
    {
      "inputs": [
        {
          "internalType": "uint256",
          "name": "projectId",
          "type": "uint256"
        }
      ],
      "name": "getVerificationReport",
      "outputs": [
        {
          "components": [
            {
              "internalType": "address",
              "name": "vvb",
              "type": "address"
            },
            {
              "internalType": "uint256",
              "name": "verificationDate",
              "type": "uint256"
            },
            {
              "internalType": "bytes32",
              "name": "verificationReportHash",
              "type": "bytes32"
            }
          ],
          "internalType": "struct TerraStakeProjects.VerificationData",
          "name": "",
          "type": "tuple"
        }
      ],
      "stateMutability": "view",
      "type": "function"
    },
    {
      "inputs": [
        {
          "internalType": "bytes32",
          "name": "role",
          "type": "bytes32"
        },
        {
          "internalType": "address",
          "name": "account",
          "type": "address"
        }
      ],
      "name": "grantRole",
      "outputs": [],
      "stateMutability": "nonpayable",
      "type": "function"
    },
    {
      "inputs": [
        {
          "internalType": "bytes32",
          "name": "role",
          "type": "bytes32"
        },
        {
          "internalType": "address",
          "name": "account",
          "type": "address"
        }
      ],
      "name": "hasRole",
      "outputs": [
        {
          "internalType": "bool",
          "name": "",
          "type": "bool"
        }
      ],
      "stateMutability": "view",
      "type": "function"
    },
    {
      "inputs": [
        {
          "internalType": "address",
          "name": "admin",
          "type": "address"
        },
        {
          "internalType": "address",
          "name": "_rewardToken",
          "type": "address"
        }
      ],
      "name": "initialize",
      "outputs": [],
      "stateMutability": "nonpayable",
      "type": "function"
    },
    {
      "inputs": [
        {
          "internalType": "uint256",
          "name": "projectId",
          "type": "uint256"
        }
      ],
      "name": "isProjectActive",
      "outputs": [
        {
          "internalType": "bool",
          "name": "",
          "type": "bool"
        }
      ],
      "stateMutability": "view",
      "type": "function"
    },
    {
      "inputs": [
        {
          "internalType": "uint256",
          "name": "",
          "type": "uint256"
        }
      ],
      "name": "methodologies",
      "outputs": [
        {
          "internalType": "string",
          "name": "name",
          "type": "string"
        },
        {
          "internalType": "string",
          "name": "description",
          "type": "string"
        },
        {
          "internalType": "string",
          "name": "version",
          "type": "string"
        },
        {
          "internalType": "bytes32",
          "name": "externalReference",
          "type": "bytes32"
        }
      ],
      "stateMutability": "view",
      "type": "function"
    },
    {
      "inputs": [],
      "name": "projectCount",
      "outputs": [
        {
          "internalType": "uint256",
          "name": "",
          "type": "uint256"
        }
      ],
      "stateMutability": "view",
      "type": "function"
    },
    {
      "inputs": [
        {
          "internalType": "uint256",
          "name": "",
          "type": "uint256"
        }
      ],
      "name": "projectMetadata",
      "outputs": [
        {
          "internalType": "string",
          "name": "name",
          "type": "string"
        },
        {
          "internalType": "string",
          "name": "description",
          "type": "string"
        },
        {
          "internalType": "string",
          "name": "location",
          "type": "string"
        },
        {
          "internalType": "string",
          "name": "impactMetrics",
          "type": "string"
        },
        {
          "internalType": "bytes32",
          "name": "ipfsHash",
          "type": "bytes32"
        },
        {
          "internalType": "bool",
          "name": "exists",
          "type": "bool"
        }
      ],
      "stateMutability": "view",
      "type": "function"
    },
    {
      "inputs": [
        {
          "internalType": "uint256",
          "name": "",
          "type": "uint256"
        }
      ],
      "name": "projectStateData",
      "outputs": [
        {
          "internalType": "enum ITerraStakeProjects.ProjectCategory",
          "name": "category",
          "type": "uint8"
        },
        {
          "internalType": "enum ITerraStakeProjects.ProjectState",
          "name": "state",
          "type": "uint8"
        },
        {
          "internalType": "uint32",
          "name": "stakingMultiplier",
          "type": "uint32"
        },
        {
          "internalType": "uint128",
          "name": "totalStaked",
          "type": "uint128"
        },
        {
          "internalType": "uint128",
          "name": "rewardPool",
          "type": "uint128"
        },
        {
          "internalType": "bool",
          "name": "isActive",
          "type": "bool"
        },
        {
          "internalType": "uint48",
          "name": "startBlock",
          "type": "uint48"
        },
        {
          "internalType": "uint48",
          "name": "endBlock",
          "type": "uint48"
        },
        {
          "internalType": "address",
          "name": "owner",
          "type": "address"
        },
        {
          "internalType": "int256",
          "name": "lastReportedValue",
          "type": "int256"
        },
        {
          "internalType": "uint256",
          "name": "lastRewardUpdate",
          "type": "uint256"
        },
        {
          "internalType": "uint256",
          "name": "accumulatedRewards",
          "type": "uint256"
        }
      ],
      "stateMutability": "view",
      "type": "function"
    },
    {
      "inputs": [],
      "name": "registrationFee",
      "outputs": [
        {
          "internalType": "uint256",
          "name": "",
          "type": "uint256"
        }
      ],
      "stateMutability": "view",
      "type": "function"
    },
    {
      "inputs": [
        {
          "internalType": "bytes32",
          "name": "role",
          "type": "bytes32"
        },
        {
          "internalType": "address",
          "name": "callerConfirmation",
          "type": "address"
        }
      ],
      "name": "renounceRole",
      "outputs": [],
      "stateMutability": "nonpayable",
      "type": "function"
    },
    {
      "inputs": [
        {
          "internalType": "bytes32",
          "name": "role",
          "type": "bytes32"
        },
        {
          "internalType": "address",
          "name": "account",
          "type": "address"
        }
      ],
      "name": "revokeRole",
      "outputs": [],
      "stateMutability": "nonpayable",
      "type": "function"
    },
    {
      "inputs": [],
      "name": "rewardToken",
      "outputs": [
        {
          "internalType": "contract IERC20",
          "name": "",
          "type": "address"
        }
      ],
      "stateMutability": "view",
      "type": "function"
    },
    {
      "inputs": [],
      "name": "rewardsContract",
      "outputs": [
        {
          "internalType": "contract ITerraStakeRewards",
          "name": "",
          "type": "address"
        }
      ],
      "stateMutability": "view",
      "type": "function"
    },
    {
      "inputs": [
        {
          "internalType": "enum ITerraStakeProjects.ProjectCategory",
          "name": "category",
          "type": "uint8"
        },
        {
          "internalType": "uint256",
          "name": "multiplier",
          "type": "uint256"
        }
      ],
      "name": "setCategoryMultiplier",
      "outputs": [],
      "stateMutability": "nonpayable",
      "type": "function"
    },
    {
      "inputs": [
        {
          "internalType": "address",
          "name": "_stakingContract",
          "type": "address"
        },
        {
          "internalType": "address",
          "name": "_rewardsContract",
          "type": "address"
        }
      ],
      "name": "setContracts",
      "outputs": [],
      "stateMutability": "nonpayable",
      "type": "function"
    },
    {
      "inputs": [
        {
          "internalType": "enum ITerraStakeProjects.ProjectCategory",
          "name": "category",
          "type": "uint8"
        },
        {
          "internalType": "uint256",
          "name": "minimumImpact",
          "type": "uint256"
        },
        {
          "internalType": "uint256",
          "name": "verificationFrequency",
          "type": "uint256"
        },
        {
          "internalType": "string[]",
          "name": "requiredDocuments",
          "type": "string[]"
        },
        {
          "internalType": "uint256",
          "name": "qualityThreshold",
          "type": "uint256"
        },
        {
          "internalType": "uint256",
          "name": "minimumScale",
          "type": "uint256"
        }
      ],
      "name": "setImpactRequirement",
      "outputs": [],
      "stateMutability": "nonpayable",
      "type": "function"
    },
    {
      "inputs": [],
      "name": "stakingContract",
      "outputs": [
        {
          "internalType": "contract ITerraStakeStaking",
          "name": "",
          "type": "address"
        }
      ],
      "stateMutability": "view",
      "type": "function"
    },
    {
      "inputs": [
        {
          "internalType": "uint256",
          "name": "projectId",
          "type": "uint256"
        },
        {
          "internalType": "bytes32",
          "name": "reportHash",
          "type": "bytes32"
        }
      ],
      "name": "submitValidation",
      "outputs": [],
      "stateMutability": "nonpayable",
      "type": "function"
    },
    {
      "inputs": [
        {
          "internalType": "uint256",
          "name": "projectId",
          "type": "uint256"
        },
        {
          "internalType": "bytes32",
          "name": "reportHash",
          "type": "bytes32"
        }
      ],
      "name": "submitVerification",
      "outputs": [],
      "stateMutability": "nonpayable",
      "type": "function"
    },
    {
      "inputs": [
        {
          "internalType": "bytes4",
          "name": "interfaceId",
          "type": "bytes4"
        }
      ],
      "name": "supportsInterface",
      "outputs": [
        {
          "internalType": "bool",
          "name": "",
          "type": "bool"
        }
      ],
      "stateMutability": "view",
      "type": "function"
    },
    {
      "inputs": [
        {
          "internalType": "uint256",
          "name": "_registrationFee",
          "type": "uint256"
        },
        {
          "internalType": "uint256",
          "name": "_verificationFee",
          "type": "uint256"
        }
      ],
      "name": "updateFeeStructure",
      "outputs": [],
      "stateMutability": "nonpayable",
      "type": "function"
    },
    {
      "inputs": [
        {
          "internalType": "uint256",
          "name": "projectId",
          "type": "uint256"
        },
        {
          "internalType": "bytes32[]",
          "name": "documentHashes",
          "type": "bytes32[]"
        }
      ],
      "name": "updateProjectDocumentation",
      "outputs": [],
      "stateMutability": "nonpayable",
      "type": "function"
    },
    {
      "inputs": [
        {
          "internalType": "uint256",
          "name": "projectId",
          "type": "uint256"
        },
        {
          "internalType": "enum ITerraStakeProjects.ProjectState",
          "name": "newState",
          "type": "uint8"
        }
      ],
      "name": "updateProjectState",
      "outputs": [],
      "stateMutability": "nonpayable",
      "type": "function"
    },
    {
      "inputs": [
        {
          "internalType": "uint256",
          "name": "",
          "type": "uint256"
        }
      ],
      "name": "validations",
      "outputs": [
        {
          "internalType": "address",
          "name": "vvb",
          "type": "address"
        },
        {
          "internalType": "uint256",
          "name": "validationDate",
          "type": "uint256"
        },
        {
          "internalType": "bytes32",
          "name": "validationReportHash",
          "type": "bytes32"
        }
      ],
      "stateMutability": "view",
      "type": "function"
    },
    {
      "inputs": [],
      "name": "verificationFee",
      "outputs": [
        {
          "internalType": "uint256",
          "name": "",
          "type": "uint256"
        }
      ],
      "stateMutability": "view",
      "type": "function"
    },
    {
      "inputs": [
        {
          "internalType": "uint256",
          "name": "",
          "type": "uint256"
        }
      ],
      "name": "verifications",
      "outputs": [
        {
          "internalType": "address",
          "name": "vvb",
          "type": "address"
        },
        {
          "internalType": "uint256",
          "name": "verificationDate",
          "type": "uint256"
        },
        {
          "internalType": "bytes32",
          "name": "verificationReportHash",
          "type": "bytes32"
        }
      ],
      "stateMutability": "view",
      "type": "function"
    }
]